veri/__init__.py
veri/client.py
veri/errors.py
veri/py.typed
veri/types.py
veri_sdk-0.1.1.dist-info/METADATA
veri_sdk-0.1.1.dist-info/WHEEL
veri_sdk-0.1.1.dist-info/RECORD
